netunnel_jwthenticator/__init__.py
netunnel_jwthenticator/plugin.py
netunnel_jwthenticator-1.0.3.dist-info/LICENSE
netunnel_jwthenticator-1.0.3.dist-info/METADATA
netunnel_jwthenticator-1.0.3.dist-info/WHEEL
netunnel_jwthenticator-1.0.3.dist-info/top_level.txt
netunnel_jwthenticator-1.0.3.dist-info/RECORD
