Metadata-Version: 2.1
Name: netunnel-jwthenticator
Version: 1.0.3
Summary: JWThenticator plugin for NETunnel
Home-page: https://github.com/claroty/netunnel-jwthenticator
Author: Claroty Open Source
Author-email: opensource@claroty.com
Maintainer: Claroty Open Source
Maintainer-email: opensource@claroty.com
License: Apache 2
Classifier: Programming Language :: Python
Classifier: Programming Language :: Python :: 3
Classifier: Programming Language :: Python :: 3.6
Classifier: Programming Language :: Python :: 3.7
Classifier: Programming Language :: Python :: 3.8
Classifier: Programming Language :: Python :: 3.9
Classifier: License :: OSI Approved :: Apache Software License
Classifier: Operating System :: OS Independent
Requires-Python: >=3.6
License-File: LICENSE
Requires-Dist: netunnel>=1.0.13
Requires-Dist: jwthenticator>=1.6.3
Requires-Dist: YURL>=1.0.0
